burrowswheeler/__init__.py
burrowswheeler-1.0.dist-info/LICENSE
burrowswheeler-1.0.dist-info/METADATA
burrowswheeler-1.0.dist-info/WHEEL
burrowswheeler-1.0.dist-info/top_level.txt
burrowswheeler-1.0.dist-info/RECORD
